coincap_fdw/__init__.py
coincap_fdw/wrapper.hy
coincap_fdw-0.0.1.dist-info/METADATA
coincap_fdw-0.0.1.dist-info/WHEEL
coincap_fdw-0.0.1.dist-info/top_level.txt
coincap_fdw-0.0.1.dist-info/RECORD
